src/__init__.py
src/count_in_list.py
ft_package_mmateo_t-1.0.dist-info/LICENSE
ft_package_mmateo_t-1.0.dist-info/METADATA
ft_package_mmateo_t-1.0.dist-info/WHEEL
ft_package_mmateo_t-1.0.dist-info/top_level.txt
ft_package_mmateo_t-1.0.dist-info/RECORD
